simple_gobang/__init__.py
simple_gobang/gobang.py
test/__init__.py
test/gobang.py
LCK_Gobang-0.1.dist-info/METADATA
LCK_Gobang-0.1.dist-info/WHEEL
LCK_Gobang-0.1.dist-info/top_level.txt
LCK_Gobang-0.1.dist-info/RECORD
