Metadata-Version: 2.1
Name: LCK-Gobang
Version: 0.1
Summary: python写的简易五子棋，对了，关于组队那个事情，队长是我，队员有张馨和吴泳朗
Home-page: https://github.com/chuunibyo-kang/simple-gobang
Author: Lam_ChingKeung
License: UNKNOWN
Platform: UNKNOWN
